llm_model/__init__.py
llm_model/attention_masks.py
llm_model/kv_cache.py
llm_model/llm_model.py
llm_model/model_config.py
llm_model/rope.py
llm_model/sparse_moe.py
llm_model/vlm_model.py
project_llm_model-0.7.8.dist-info/METADATA
project_llm_model-0.7.8.dist-info/WHEEL
project_llm_model-0.7.8.dist-info/top_level.txt
project_llm_model-0.7.8.dist-info/RECORD
