Metadata-Version: 2.4
Name: project_llm_model
Version: 0.7.8
Summary: LLM and VLM model
Author: qibin
Author-email: qibin0506@gmail.com
Dynamic: author
Dynamic: author-email
Dynamic: summary
